LICENSE.txt
evo_package_assistant/__init__.py
evo_package_assistant/automation/api.yaml
evo_package_assistant/automation/entity.yaml
evo_package_assistant/control/CAssistantApi.py
evo_package_assistant/control/CAssistantCallback.py
evo_package_assistant/control/__init__.py
evo_package_assistant/entity/EAssistant.py
evo_package_assistant/entity/EAssistantAction.py
evo_package_assistant/entity/EAssistantAdmin.py
evo_package_assistant/entity/EAssistantCallbackItem.py
evo_package_assistant/entity/EAssistantMap.py
evo_package_assistant/entity/EAssistantMessage.py
evo_package_assistant/entity/EAssistantQuery.py
evo_package_assistant/entity/EAssistantTool.py
evo_package_assistant/entity/EAssistantToolParam.py
evo_package_assistant/entity/EAssistantUser.py
evo_package_assistant/entity/EnumAssistantRole.py
evo_package_assistant/entity/__init__.py
evo_package_assistant/utility/IuAssistant.py
evo_package_assistant/utility/UAssistantApi.py
evo_package_assistant/utility/__init__.py
evo_package_assistant-2024.10.22326.dist-info/LICENSE.txt
evo_package_assistant-2024.10.22326.dist-info/METADATA
evo_package_assistant-2024.10.22326.dist-info/WHEEL
evo_package_assistant-2024.10.22326.dist-info/RECORD
